{
  "토막낸생선": {
    "0": {
      "buy_price": 0,
      "fee": 0,
      "count": 7,
      "market_price": 242,
      "market_price_time": "2025-07-12 23:30:18"
    },
    "category": "요리",
    "enchant": {
      "0": {
        "buy_price": 0,
        "fee": 0,
        "count": 355,
        "market_price": 272,
        "market_price_time": "2025-07-13 14:30:27"
      }
    }
  },
  "해조": {
    "0": {
      "buy_price": 0,
      "fee": 0,
      "count": 0,
      "market_price": 0,
      "market_price_time": null
    }
  },
  "당근": {
    "0": {
      "buy_price": 0,
      "fee": 0,
      "count": 0,
      "market_price": 354,
      "market_price_time": "2025-07-12 23:13:43"
    },
    "category": "",
    "enchant": {
      "0": {
        "buy_price": 0,
        "fee": 0,
        "count": 0,
        "market_price": 328,
        "market_price_time": "2025-07-13 16:55:11"
      }
    }
  },
  "장인낚시꾼의일지": {
    "0": {
      "buy_price": 996,
      "fee": 0,
      "count": 0,
      "market_price": 8959,
      "market_price_time": "2025-07-12 23:48:46"
    }
  },
  "철광석": {
    "0": {
      "buy_price": 0,
      "fee": 0,
      "count": 0,
      "market_price": 0,
      "market_price_time": null
    },
    "category": "",
    "enchant": {
      "0": {
        "buy_price": 0,
        "fee": 0,
        "count": 0,
        "market_price": 0,
        "market_price_time": null
      }
    }
  },
  "기본피시소스": {
    "category": "요리",
    "enchant": {
      "0": {
        "buy_price": 0,
        "fee": 0,
        "count": 0,
        "market_price": 4300,
        "market_price_time": "2025-07-13 11:14:09"
      }
    }
  },
  "입문자의곡괭이": {
    "0": {
      "buy_price": 0,
      "fee": 0,
      "count": 0,
      "market_price": 19,
      "market_price_time": "2025-07-12 23:13:59"
    }
  },
  "기본낚시미끼": {
    "0": {
      "buy_price": 0,
      "fee": 0,
      "count": 0,
      "market_price": 232,
      "market_price_time": "2025-07-12 23:14:04"
    }
  },
  "초심자의가방": {
    "0": {
      "buy_price": 0,
      "fee": 0,
      "count": 0,
      "market_price": 762,
      "market_price_time": "2025-07-12 23:25:00"
    }
  },
  "깔끔한직물": {
    "0": {
      "buy_price": 0,
      "fee": 446,
      "count": 150,
      "market_price": 0,
      "market_price_time": null
    },
    "category": "",
    "enchant": {
      "0": {
        "buy_price": 0,
        "fee": 446,
        "count": 169,
        "market_price": 0,
        "market_price_time": null
      }
    },
    "count": 162,
    "fee": 3
  },
  "괜찮은직물": {
    "0": {
      "buy_price": 0,
      "fee": 465,
      "count": 52,
      "market_price": 0,
      "market_price_time": null
    }
  },
  "로우리버게": {
    "category": "생선",
    "enchant": {
      "0": {
        "buy_price": 0,
        "fee": 0,
        "count": 0,
        "market_price": 2200,
        "market_price_time": "2025-07-13 11:18:18"
      }
    }
  },
  "소나무원목": {
    "0": {
      "buy_price": 0,
      "fee": 0,
      "count": 0,
      "market_price": 143,
      "market_price_time": "2025-07-12 23:14:28"
    },
    "1": {
      "buy_price": 0,
      "fee": 0,
      "count": 0,
      "market_price": 148,
      "market_price_time": "2025-07-12 23:16:43"
    }
  },
  "드라이브룩게": {
    "0": {
      "buy_price": 0,
      "fee": 0,
      "count": 0,
      "market_price": 4903,
      "market_price_time": "2025-07-12 23:14:31"
    }
  },
  "삼나무원목": {
    "0": {
      "buy_price": 0,
      "fee": 0,
      "count": 0,
      "market_price": 272,
      "market_price_time": "2025-07-12 23:14:35"
    },
    "category": "",
    "enchant": {
      "0": {
        "buy_price": 0,
        "fee": 0,
        "count": 0,
        "market_price": 297,
        "market_price_time": "2025-07-13 17:10:36"
      }
    }
  },
  "소나무판자": {
    "0": {
      "buy_price": 0,
      "fee": 536,
      "count": 0,
      "market_price": 324,
      "market_price_time": "2025-07-12 23:14:38"
    },
    "category": "",
    "enchant": {
      "0": {
        "buy_price": 0,
        "fee": 117,
        "count": 16,
        "market_price": 324,
        "market_price_time": "2025-07-13 17:05:30"
      }
    }
  },
  "전문가의수송용황소": {
    "0": {
      "buy_price": 99985,
      "fee": 0,
      "count": 0,
      "market_price": 99985,
      "market_price_time": "2025-07-12 23:14:41"
    }
  },
  "숙련자의망토": {
    "0": {
      "buy_price": 0,
      "fee": 0,
      "count": 0,
      "market_price": 2191,
      "market_price_time": "2025-07-12 23:21:18"
    }
  },
  "숙련자의가방": {
    "0": {
      "buy_price": 0,
      "fee": 0,
      "count": 0,
      "market_price": 4052,
      "market_price_time": "2025-07-12 23:21:59"
    }
  },
  "초심자의학자샌들": {
    "0": {
      "buy_price": 0,
      "fee": 0,
      "count": 0,
      "market_price": 455,
      "market_price_time": "2025-07-12 23:22:52"
    }
  },
  "초심자의파이어스태프": {
    "0": {
      "buy_price": 0,
      "fee": 0,
      "count": 0,
      "market_price": 478,
      "market_price_time": "2025-07-12 23:23:25"
    }
  },
  "숙련자의용병자켓": {
    "0": {
      "buy_price": 0,
      "fee": 0,
      "count": 0,
      "market_price": 2879,
      "market_price_time": "2025-07-12 23:24:00"
    }
  },
  "초심자의학자두건": {
    "0": {
      "buy_price": 0,
      "fee": 0,
      "count": 0,
      "market_price": 415,
      "market_price_time": "2025-07-12 23:25:31"
    }
  },
  "초심자의학자로브": {
    "0": {
      "buy_price": 0,
      "fee": 0,
      "count": 0,
      "market_price": 237,
      "market_price_time": "2025-07-12 23:26:11"
    }
  },
  "숙련자의용병후드": {
    "0": {
      "buy_price": 0,
      "fee": 0,
      "count": 0,
      "market_price": 1519,
      "market_price_time": "2025-07-12 23:26:46"
    }
  },
  "장인벌목꾼의일지": {
    "0": {
      "buy_price": 1287,
      "fee": 0,
      "count": 0,
      "market_price": 4889,
      "market_price_time": "2025-07-12 23:27:44"
    }
  },
  "숙련자의용병신발": {
    "0": {
      "buy_price": 0,
      "fee": 0,
      "count": 0,
      "market_price": 1340,
      "market_price_time": "2025-07-12 23:28:28"
    }
  },
  "마스터의기사아머": {
    "0": {
      "buy_price": 0,
      "fee": 0,
      "count": 0,
      "market_price": 22079,
      "market_price_time": "2025-07-12 23:29:06"
    }
  },
  "화이트포그스내퍼": {
    "0": {
      "buy_price": 0,
      "fee": 0,
      "count": 0,
      "market_price": 2589,
      "market_price_time": "2025-07-12 23:29:39"
    }
  },
  "사암": {
    "0": {
      "buy_price": 0,
      "fee": 0,
      "count": 0,
      "market_price": 113,
      "market_price_time": "2025-07-12 23:31:27"
    }
  },
  "사암석괴": {
    "0": {
      "buy_price": 0,
      "fee": 0,
      "count": 0,
      "market_price": 190,
      "market_price_time": "2025-07-12 23:32:23"
    }
  },
  "숙련자의낚싯대": {
    "0": {
      "buy_price": 0,
      "fee": 0,
      "count": 0,
      "market_price": 1629,
      "market_price_time": "2025-07-12 23:33:04"
    }
  },
  "트래버틴석괴": {
    "0": {
      "buy_price": 0,
      "fee": 0,
      "count": 0,
      "market_price": 191,
      "market_price_time": "2025-07-12 23:33:37"
    }
  },
  "장인의수송용황소": {
    "0": {
      "buy_price": 0,
      "fee": 0,
      "count": 0,
      "market_price": 12170,
      "market_price_time": "2025-07-12 23:34:48"
    }
  },
  "얇은가죽": {
    "0": {
      "buy_price": 0,
      "fee": 0,
      "count": 0,
      "market_price": 103,
      "market_price_time": "2025-07-12 23:40:05"
    }
  },
  "가공된피혁": {
    "0": {
      "buy_price": 0,
      "fee": 0,
      "count": 4,
      "market_price": 250,
      "market_price_time": "2025-07-12 23:41:15"
    }
  },
  "적당한가죽": {
    "0": {
      "buy_price": 0,
      "fee": 0,
      "count": 0,
      "market_price": 100,
      "market_price_time": "2025-07-12 23:41:58"
    },
    "3": {
      "buy_price": 0,
      "fee": 0,
      "count": 0,
      "market_price": 9479,
      "market_price_time": "2025-07-12 23:44:45"
    },
    "2": {
      "buy_price": 0,
      "fee": 0,
      "count": 0,
      "market_price": 1450,
      "market_price_time": "2025-07-12 23:45:14"
    },
    "1": {
      "buy_price": 0,
      "fee": 0,
      "count": 0,
      "market_price": 173,
      "market_price_time": "2025-07-12 23:45:57"
    },
    "category": "분류없음",
    "enchant": {
      "2": {
        "buy_price": 0,
        "fee": 0,
        "count": 3,
        "market_price": 1222,
        "market_price_time": "2025-07-13 17:09:16"
      }
    }
  },
  "튼튼한가죽": {
    "0": {
      "buy_price": 0,
      "fee": 0,
      "count": 0,
      "market_price": 0,
      "market_price_time": null
    },
    "1": {
      "buy_price": 0,
      "fee": 0,
      "count": 0,
      "market_price": 3427,
      "market_price_time": "2025-07-12 23:44:09"
    }
  },
  "점박이송어": {
    "category": "생선",
    "enchant": {
      "0": {
        "buy_price": 0,
        "fee": 0,
        "count": 0,
        "market_price": 1411,
        "market_price_time": "2025-07-13 11:18:24"
      }
    }
  },
  "푸른비늘강꼬치고기": {
    "category": "생선",
    "enchant": {
      "0": {
        "buy_price": 0,
        "fee": 0,
        "count": 0,
        "market_price": 875,
        "market_price_time": "2025-07-13 11:18:30"
      }
    }
  },
  "알비온농어": {
    "category": "생선",
    "enchant": {
      "0": {
        "buy_price": 0,
        "fee": 0,
        "count": 0,
        "market_price": 682,
        "market_price_time": "2025-07-13 11:18:39"
      }
    }
  },
  "줄무늬잉어": {
    "category": "생선",
    "enchant": {
      "0": {
        "buy_price": 0,
        "fee": 0,
        "count": 0,
        "market_price": 423,
        "market_price_time": "2025-07-13 11:18:46"
      }
    }
  },
  "그린리버장어": {
    "category": "생선",
    "enchant": {
      "0": {
        "buy_price": 0,
        "fee": 0,
        "count": 0,
        "market_price": 2245,
        "market_price_time": "2025-07-13 11:18:53"
      }
    }
  },
  "스톤스트림떠돌이": {
    "category": "생선",
    "enchant": {
      "0": {
        "buy_price": 0,
        "fee": 0,
        "count": 0,
        "market_price": 2200,
        "market_price_time": "2025-07-13 11:18:59"
      }
    }
  },
  "업랜드콜드아이": {
    "category": "생선",
    "enchant": {
      "0": {
        "buy_price": 0,
        "fee": 0,
        "count": 0,
        "market_price": 2228,
        "market_price_time": "2025-07-13 11:47:46"
      }
    }
  },
  "수확숙련자의일지": {
    "category": "분류없음",
    "enchant": {
      "0": {
        "buy_price": 2500,
        "fee": 0,
        "count": 1,
        "market_price": 2500,
        "market_price_time": "2025-07-13 11:59:52"
      }
    }
  },
  "전문가사냥터지기의일지": {
    "category": "분류없음",
    "enchant": {
      "0": {
        "buy_price": 4400,
        "fee": 0,
        "count": 1,
        "market_price": 4400,
        "market_price_time": "2025-07-13 12:01:42"
      }
    }
  },
  "숙련자탐광자의일지": {
    "category": "분류없음",
    "enchant": {
      "0": {
        "buy_price": 4000,
        "fee": 0,
        "count": 1,
        "market_price": 4000,
        "market_price_time": "2025-07-13 12:02:15"
      }
    }
  },
  "전문가벌목꾼의일지": {
    "category": "분류없음",
    "enchant": {
      "0": {
        "buy_price": 5990,
        "fee": 0,
        "count": 1,
        "market_price": 5990,
        "market_price_time": "2025-07-13 12:03:27"
      }
    }
  },
  "구리주괴": {
    "category": "분류없음",
    "enchant": {
      "0": {
        "buy_price": 0,
        "fee": 0,
        "count": 0,
        "market_price": 26,
        "market_price_time": "2025-07-13 16:57:16"
      }
    }
  },
  "아마": {
    "category": "분류없음",
    "enchant": {
      "0": {
        "buy_price": 0,
        "fee": 0,
        "count": 0,
        "market_price": 0,
        "market_price_time": null
      }
    }
  },
  "단순한직물": {
    "category": "분류없음",
    "enchant": {
      "0": {
        "buy_price": 0,
        "fee": 0,
        "count": 185,
        "market_price": 0,
        "market_price_time": null
      }
    }
  },
  "구리광석": {
    "category": "분류없음",
    "enchant": {
      "0": {
        "buy_price": 0,
        "fee": 0,
        "count": 0,
        "market_price": 0,
        "market_price_time": null
      }
    }
  },
  "아연광석": {
    "category": "분류없음",
    "enchant": {
      "0": {
        "buy_price": 0,
        "fee": 0,
        "count": 0,
        "market_price": 98,
        "market_price_time": "2025-07-13 14:25:50"
      }
    }
  },
  "청동주괴": {
    "category": "분류없음",
    "enchant": {
      "0": {
        "buy_price": 0,
        "fee": 448,
        "count": 0,
        "market_price": 0,
        "market_price_time": null
      }
    }
  },
  "강철주괴": {
    "category": "분류없음",
    "enchant": {
      "0": {
        "buy_price": 0,
        "fee": 1152,
        "count": 0,
        "market_price": 332,
        "market_price_time": "2025-07-13 14:26:44"
      }
    }
  },
  "헤비가죽": {
    "category": "분류없음",
    "enchant": {
      "0": {
        "buy_price": 0,
        "fee": 0,
        "count": 0,
        "market_price": 420,
        "market_price_time": "2025-07-13 14:13:54"
      }
    }
  },
  "밤나무판자": {
    "category": "분류없음",
    "enchant": {
      "0": {
        "buy_price": 0,
        "fee": 27,
        "count": 12,
        "market_price": 0,
        "market_price_time": null
      }
    }
  }
}